typed_coinbaseadvanced/__init__.py
typed_coinbaseadvanced-0.1.0.dist-info/METADATA
typed_coinbaseadvanced-0.1.0.dist-info/WHEEL
typed_coinbaseadvanced-0.1.0.dist-info/top_level.txt
typed_coinbaseadvanced-0.1.0.dist-info/RECORD
